pyring_buffer/__init__.py
pyring_buffer-1.0.2.dist-info/licenses/LICENSE.md
pyring_buffer-1.0.2.dist-info/METADATA
pyring_buffer-1.0.2.dist-info/WHEEL
pyring_buffer-1.0.2.dist-info/top_level.txt
pyring_buffer-1.0.2.dist-info/zip-safe
pyring_buffer-1.0.2.dist-info/RECORD
