Metadata-Version: 2.4
Name: pyring_buffer
Version: 1.0.2
Summary: A pure Python ring buffer for bytes
Author-email: Michael Hansen <mike@rhasspy.org>
License: Apache-2.0
Project-URL: Source Code, http://github.com/rhasspy/pyring-buffer
Keywords: ring,circular,buffer
Platform: any
Classifier: Development Status :: 3 - Alpha
Classifier: Intended Audience :: Developers
Classifier: Topic :: Text Processing :: Linguistic
Classifier: License :: OSI Approved :: Apache Software License
Classifier: Programming Language :: Python :: 3.8
Classifier: Programming Language :: Python :: 3.9
Classifier: Programming Language :: Python :: 3.10
Classifier: Programming Language :: Python :: 3.11
Classifier: Programming Language :: Python :: 3.12
Classifier: Programming Language :: Python :: 3.13
Requires-Python: >=3.9.0
License-File: LICENSE.md
Provides-Extra: dev
Requires-Dist: black==22.12.0; extra == "dev"
Requires-Dist: flake8==6.0.0; extra == "dev"
Requires-Dist: isort==5.11.3; extra == "dev"
Requires-Dist: mypy==0.991; extra == "dev"
Requires-Dist: pylint==2.15.9; extra == "dev"
Requires-Dist: pytest==7.4.4; extra == "dev"
Requires-Dist: build==1.2.2; extra == "dev"
Dynamic: license-file
